atlite/__init__.py
atlite/aggregate.py
atlite/convert.py
atlite/csp.py
atlite/cutout.py
atlite/data.py
atlite/gis.py
atlite/hydro.py
atlite/resource.py
atlite/utils.py
atlite/wind.py
atlite/datasets/__init__.py
atlite/datasets/cordex.py
atlite/datasets/era5.py
atlite/datasets/gebco.py
atlite/datasets/ncep.py
atlite/datasets/sarah.py
atlite/pv/__init__.py
atlite/pv/irradiation.py
atlite/pv/orientation.py
atlite/pv/solar_panel_model.py
atlite/pv/solar_position.py
atlite/resources/cspinstallation/SAM_parabolic_trough.yaml
atlite/resources/cspinstallation/SAM_solar_tower.yaml
atlite/resources/cspinstallation/lossless_installation.yaml
atlite/resources/solarpanel/CSi.yaml
atlite/resources/solarpanel/CdTe.yaml
atlite/resources/solarpanel/KANENA.yaml
atlite/resources/windturbine/Bonus_B1000_1000kW.yaml
atlite/resources/windturbine/Enercon_E101_3000kW.yaml
atlite/resources/windturbine/Enercon_E126_7500kW.yaml
atlite/resources/windturbine/Enercon_E82_3000kW.yaml
atlite/resources/windturbine/NREL_ReferenceTurbine_2016CACost_10MW_offshore.yaml
atlite/resources/windturbine/NREL_ReferenceTurbine_2016CACost_6MW_offshore.yaml
atlite/resources/windturbine/NREL_ReferenceTurbine_2016CACost_8MW_offshore.yaml
atlite/resources/windturbine/NREL_ReferenceTurbine_2019ORCost_12MW_offshore.yaml
atlite/resources/windturbine/NREL_ReferenceTurbine_2019ORCost_15MW_offshore.yaml
atlite/resources/windturbine/NREL_ReferenceTurbine_2020ATB_12MW_offshore.yaml
atlite/resources/windturbine/NREL_ReferenceTurbine_2020ATB_15MW_offshore.yaml
atlite/resources/windturbine/NREL_ReferenceTurbine_2020ATB_18MW_offshore.yaml
atlite/resources/windturbine/NREL_ReferenceTurbine_2020ATB_4MW.yaml
atlite/resources/windturbine/NREL_ReferenceTurbine_2020ATB_5.5MW.yaml
atlite/resources/windturbine/NREL_ReferenceTurbine_2020ATB_7MW.yaml
atlite/resources/windturbine/NREL_ReferenceTurbine_5MW_offshore.yaml
atlite/resources/windturbine/Siemens_SWT_107_3600kW.yaml
atlite/resources/windturbine/Siemens_SWT_2300kW.yaml
atlite-0.4.0.dist-info/AUTHORS.rst
atlite-0.4.0.dist-info/LICENSE
atlite-0.4.0.dist-info/METADATA
atlite-0.4.0.dist-info/WHEEL
atlite-0.4.0.dist-info/top_level.txt
atlite-0.4.0.dist-info/RECORD
