Metadata-Version: 2.2
Name: atlite
Version: 0.4.0
Summary: Library for fetching and converting weather data to power systems data
Author-email: Contributors to atlite <jonas.hoersch@posteo.de>
License: MIT License
Project-URL: Homepage, https://github.com/PyPSA/atlite
Project-URL: Source, https://github.com/PyPSA/atlite
Project-URL: Documentation, https://atlite.readthedocs.io/en/latest/
Classifier: Programming Language :: Python :: 3.10
Classifier: Programming Language :: Python :: 3.11
Classifier: Programming Language :: Python :: 3.12
Classifier: Programming Language :: Python :: 3.13
Classifier: Development Status :: 3 - Alpha
Classifier: Environment :: Console
Classifier: Intended Audience :: Science/Research
Classifier: License :: OSI Approved :: MIT License
Classifier: Natural Language :: English
Classifier: Operating System :: OS Independent
Requires-Python: >=3.10
License-File: LICENSE
License-File: AUTHORS.rst
Requires-Dist: typing-extensions
Requires-Dist: numpy
Requires-Dist: scipy
Requires-Dist: pandas>=0.25
Requires-Dist: bottleneck
Requires-Dist: numexpr
Requires-Dist: xarray>=2024.03.0
Requires-Dist: netcdf4
Requires-Dist: dask>=2021.10.0
Requires-Dist: toolz
Requires-Dist: requests
Requires-Dist: pyyaml
Requires-Dist: rasterio!=1.4.0,!=1.4.1
Requires-Dist: shapely
Requires-Dist: progressbar2
Requires-Dist: tqdm
Requires-Dist: pyproj>=2
Requires-Dist: geopandas
Requires-Dist: cdsapi>=0.7.4
Provides-Extra: dev
Requires-Dist: pre-commit; extra == "dev"
Requires-Dist: pytest; extra == "dev"
Requires-Dist: pytest-cov; extra == "dev"
Requires-Dist: matplotlib; extra == "dev"
Requires-Dist: ruff; extra == "dev"
Provides-Extra: docs
Requires-Dist: numpydoc==1.8.0; extra == "docs"
Requires-Dist: sphinx==8.0.2; extra == "docs"
Requires-Dist: sphinx-book-theme==1.1.3; extra == "docs"
Requires-Dist: nbsphinx==0.9.5; extra == "docs"
Requires-Dist: nbsphinx-link==1.3.0; extra == "docs"
Requires-Dist: docutils==0.20; extra == "docs"
